{"moves":{"0":[{"mine":0,"opponent":0}],"1":[{"risk":0.10416666666666667,"profitToRisk":28.799999999999997,"profit":3},{"risk":0.20833333333333334,"profitToRisk":38.4,"profit":8},{"risk":0.3125,"profitToRisk":54.4,"profit":17},{"risk":0.4166666666666667,"profitToRisk":48,"profit":20},{"endTurn":true},{"mine":20,"opponent":0}],"2":[{"risk":0.09090909090909091,"profitToRisk":-33,"profit":-3},{"risk":0.4772727272727273,"profitToRisk":31.428571428571427,"profit":15},{"risk":0.5681818181818182,"profitToRisk":29.919999999999998,"profit":17},{"mine":20,"opponent":17}],"3":[{"risk":0.13157894736842105,"profitToRisk":53.2,"profit":7},{"risk":0.4473684210526315,"profitToRisk":42.47058823529412,"profit":19},{"risk":0.6578947368421052,"profitToRisk":42.56,"profit":28},{"mine":48,"opponent":7}],"4":[{"mine":45,"opponent":7}],"5":[{"risk":0.12121212121212122,"profitToRisk":-8.25,"profit":-1},{"risk":0.5757575757575758,"profitToRisk":5.2105263157894735,"profit":3},{"risk":0.6666666666666667,"profitToRisk":5.999999999999999,"profit":4},{"mine":54,"opponent":0}],"6":[{"risk":0.1111111111111111,"profitToRisk":-18,"profit":-2},{"endTurn":true},{"mine":50,"opponent":5}],"7":[{"risk":0.11538461538461539,"profitToRisk":34.666666666666664,"profit":4},{"mine":50,"opponent":5}],"8":[{"risk":0.25,"profitToRisk":-12,"profit":-3},{"endTurn":true},{"mine":50,"opponent":11}],"9":[{"mine":50,"opponent":11}],"10":[{"risk":0.09090909090909091,"profitToRisk":22,"profit":2},{"mine":50,"opponent":26}],"11":[{"risk":0.2222222222222222,"profitToRisk":22.5,"profit":5},{"risk":0.3333333333333333,"profitToRisk":6,"profit":2},{"risk":0.38888888888888884,"profitToRisk":0,"profit":0},{"mine":55,"opponent":21}],"12":[{"risk":0.07692307692307693,"profitToRisk":-13,"profit":-1},{"endTurn":true},{"mine":50,"opponent":27}],"13":[{"risk":0.3333333333333333,"profitToRisk":6,"profit":2},{"mine":47,"opponent":27}],"14":[{"risk":0.2,"profitToRisk":40,"profit":8},{"risk":0.30000000000000004,"profitToRisk":29.999999999999996,"profit":9},{"risk":0.4,"profitToRisk":25,"profit":10},{"risk":0.5,"profitToRisk":14,"profit":7},{"endTurn":true},{"mine":47,"opponent":52}],"15":[{"risk":0.16666666666666666,"profitToRisk":42,"profit":7},{"mine":55,"opponent":52}],"16":[{"risk":0.5,"profitToRisk":8,"profit":4},{"risk":0.75,"profitToRisk":-2.6666666666666665,"profit":-2},{"mine":52,"opponent":58}],"17":[{"mine":60,"opponent":57}]},"matchid":"63dc43d1b8892273df9ecf88","mine":60,"opponent":57}